dbt2tmdl/__init__.py
dbt2tmdl/generator.py
dbt2tmdl/loader.py
dbt2tmdl/main.py
dbt2tmdl/models.py
dbt2tmdl-0.1.1a1.dist-info/METADATA
dbt2tmdl-0.1.1a1.dist-info/WHEEL
dbt2tmdl-0.1.1a1.dist-info/entry_points.txt
dbt2tmdl-0.1.1a1.dist-info/RECORD
